storytime/__init__.py
storytime/actors.py
storytime/engine.py
storytime/examples.py
storytime/history.py
storytime/meta.py
storytime/out.py
storytime/setting.py
storytime/time.py
storytime/universe.py
storytime/entities/__init__.py
storytime/spatial/__init__.py
storytime/spatial/graphs.py
storytime/spatial/projections.py
storytime/spatial/surfaces.py
storytime/spatial/transformations.py
storytime/spatial/units.py
storytime-0.0.0.dist-info/DESCRIPTION.rst
storytime-0.0.0.dist-info/METADATA
storytime-0.0.0.dist-info/RECORD
storytime-0.0.0.dist-info/WHEEL
storytime-0.0.0.dist-info/entry_points.txt
storytime-0.0.0.dist-info/metadata.json
storytime-0.0.0.dist-info/top_level.txt
