Metadata-Version: 2.0
Name: storytime
Version: 0.0.0
Summary: No Description
